lifepo4weredPyController/Battery.py
lifepo4weredPyController/Led.py
lifepo4weredPyController/LedStateEnum.py
lifepo4weredPyController/Lifepo4wered.py
lifepo4weredPyController/Reader.py
lifepo4weredPyController/Touch.py
lifepo4weredPyController/TouchStateEnum.py
lifepo4weredPyController/USBPowerSource.py
lifepo4weredPyController/WakeTimer.py
lifepo4weredPyController/__init__.py
lifepo4weredPyController/packageExposedServices.py
lifepo4weredPyController/packageInfo.py
lifepo4weredPyController/helpers/SetHelper.py
lifepo4weredPyController/helpers/__init__.py
lifepo4weredPyController-0.2.4.dist-info/DESCRIPTION.rst
lifepo4weredPyController-0.2.4.dist-info/METADATA
lifepo4weredPyController-0.2.4.dist-info/RECORD
lifepo4weredPyController-0.2.4.dist-info/WHEEL
lifepo4weredPyController-0.2.4.dist-info/metadata.json
lifepo4weredPyController-0.2.4.dist-info/top_level.txt
