Metadata-Version: 2.0
Name: lifepo4weredPyController
Version: 0.2.4
Summary: Observable data and class oriented of Lifepo4wered battery power module.
Home-page: https://github.com/fredericklussier/Lifepo4weredPyController
Author: Frederick Lussier
Author-email: frederick.lussier@hotmail.com
License: MIT
Download-URL: https://github.com/fredericklussier/Lifepo4weredPyController/tree/0.2.4
Keywords: raspberry-pi,raspberrypi,lifepo4wered,lifepo4wered-pi,lifepo4weredpi,battery,powersource
Platform: UNKNOWN
Classifier: Development Status :: 4 - Beta
Classifier: Intended Audience :: Developers
Classifier: License :: OSI Approved :: MIT License
Classifier: Programming Language :: Python :: 3 :: Only
Classifier: Programming Language :: Python :: 3.5
Classifier: Programming Language :: Python :: 3.6
Classifier: Natural Language :: English
Requires-Dist: tinyPeriodicTask (>=1.3.1)
Requires-Dist: observablePy (>=0.2.2)
Requires-Dist: lifepo4weredPy (>=0.1.0)
